arrayflux/__init__.py
arrayflux/api.py
arrayflux/core.py
arrayflux/rolling.py
arrayflux-0.1.1.dist-info/licenses/LICENSE
arrayflux-0.1.1.dist-info/METADATA
arrayflux-0.1.1.dist-info/WHEEL
arrayflux-0.1.1.dist-info/top_level.txt
arrayflux-0.1.1.dist-info/RECORD
