Metadata-Version: 2.4
Name: arrayflux
Version: 0.1.1
Summary: NumPy ndarray subclass with rolling-window operations.
Author: Lorenzo Santarsieri
License: MIT
Requires-Python: >=3.10
License-File: LICENSE
Requires-Dist: numpy>=2.2.6
Requires-Dist: scipy>=1.15.3
Dynamic: license-file
